homelab_assistant/__init__.py
homelab_assistant/main.py
homelab_assistant/helpers/__init__.py
homelab_assistant/helpers/portainer.py
homelab_assistant/models/__init__.py
homelab_assistant/models/config.py
homelab_assistant/runners/__init__.py
homelab_assistant/runners/export.py
homelab_assistant/runners/sync.py
homelab_assistant/utils/__init__.py
homelab_assistant/utils/cli.py
homelab_assistant-1.4.0.dist-info/licenses/LICENSE
homelab_assistant-1.4.0.dist-info/METADATA
homelab_assistant-1.4.0.dist-info/WHEEL
homelab_assistant-1.4.0.dist-info/entry_points.txt
homelab_assistant-1.4.0.dist-info/top_level.txt
homelab_assistant-1.4.0.dist-info/RECORD
