Metadata-Version: 2.4
Name: homelab-assistant
Version: 1.4.0
Summary: Automation tools for Homelab deployments, using Portainer's API
Requires-Python: >=3.12
License-File: LICENSE
Requires-Dist: fluffless>=0.0.3
Requires-Dist: pydantic>=2.12.5
Requires-Dist: pyyaml>=6.0.3
Requires-Dist: requests>=2.32.5
Provides-Extra: dev
Requires-Dist: fluffless[dev]>=0.0.3; extra == "dev"
Dynamic: license-file
